[{"favourite":20144,"name":"桃华月惮","url":"http://bangumi.bilibili.com/anime/1310","count":174000.0},{"favourite":20085,"name":"妖狐×仆SS SP","url":"http://bangumi.bilibili.com/anime/5859","count":554000.0},{"favourite":20084,"name":"阿莱蒂公主","url":"http://bangumi.bilibili.com/anime/3085","count":50000.0},{"favourite":20005,"name":"×××HOLiC 仲夏夜之梦","url":"http://bangumi.bilibili.com/anime/3396","count":212000.0},{"favourite":19949,"name":"南方公园 第十一季","url":"http://bangumi.bilibili.com/anime/2182","count":627000.0},{"favourite":19946,"name":"网球并不可笑嘛 第七季","url":"http://bangumi.bilibili.com/anime/3234","count":840000.0},{"favourite":19909,"name":"漫研部～Surgical Friends～","url":"http://bangumi.bilibili.com/anime/5868","count":310000.0},{"favourite":19897,"name":"为什么猫都叫不来","url":"http://bangumi.bilibili.com/anime/4106","count":422000.0},{"favourite":19860,"name":"白砂糖战士","url":"http://bangumi.bilibili.com/anime/4234","count":142000.0},{"favourite":19840,"name":"天地无用！ 剧场版","url":"http://bangumi.bilibili.com/anime/1618","count":64000.0},{"favourite":19817,"name":"逮捕令 第一季","url":"http://bangumi.bilibili.com/anime/1340","count":345000.0},{"favourite":19772,"name":"夏娃的时间","url":"http://bangumi.bilibili.com/anime/3339","count":118000.0},{"favourite":19746,"name":"人鱼又上钩","url":"http://bangumi.bilibili.com/anime/570","count":1787000.0},{"favourite":19708,"name":"滑头鬼之孙 ～奴良组事始～","url":"http://bangumi.bilibili.com/anime/3798","count":188000.0},{"favourite":19675,"name":"Happiness!","url":"http://bangumi.bilibili.com/anime/1426","count":48000.0},{"favourite":19667,"name":"无罪的维纳斯","url":"http://bangumi.bilibili.com/anime/1437","count":134000.0},{"favourite":19659,"name":"青之六号","url":"http://bangumi.bilibili.com/anime/3274","count":53000.0},{"favourite":19648,"name":"摸索吧！部活剧","url":"http://bangumi.bilibili.com/anime/1578","count":112000.0},{"favourite":19648,"name":"玛莉亚†狂热 第二季","url":"http://bangumi.bilibili.com/anime/921","count":736000.0},{"favourite":19627,"name":"VENUS PROJECT -CLIMAX-","url":"http://bangumi.bilibili.com/anime/2599","count":681000.0}]