[{"favourite":4860,"name":"魔法咪路咪路 Charming","url":"http://bangumi.bilibili.com/anime/3917","count":0.0},{"favourite":4844,"name":"DI GI CHARAT 第一季","url":"http://bangumi.bilibili.com/anime/2085","count":20000.0},{"favourite":4835,"name":"超时空要塞 可曾记得爱","url":"http://bangumi.bilibili.com/anime/3557","count":87000.0},{"favourite":4833,"name":"一期一会~你的话语~","url":"http://bangumi.bilibili.com/anime/1006","count":25000.0},{"favourite":4828,"name":"足球小将 平成版","url":"http://bangumi.bilibili.com/anime/2139","count":104000.0},{"favourite":4815,"name":"太空堡垒 第一季","url":"http://bangumi.bilibili.com/anime/1805","count":100000.0},{"favourite":4812,"name":"遥远时空中 紫阳花物语","url":"http://bangumi.bilibili.com/anime/1883","count":26000.0},{"favourite":4810,"name":"当心蝙蝠侠","url":"http://bangumi.bilibili.com/anime/1734","count":337000.0},{"favourite":4806,"name":"攻壳机动队 塔奇克马的日常","url":"http://bangumi.bilibili.com/anime/5171","count":41000.0},{"favourite":4800,"name":"艾莉森与莉莉亚","url":"http://bangumi.bilibili.com/anime/1240","count":84000.0},{"favourite":4782,"name":"暖暖日记 2nd","url":"http://bangumi.bilibili.com/anime/6041","count":79000.0},{"favourite":4781,"name":"BALDR FORCE EXE RESOLUTION","url":"http://bangumi.bilibili.com/anime/4875","count":52000.0},{"favourite":4770,"name":"宝石宠物 第四季","url":"http://bangumi.bilibili.com/anime/125","count":95000.0},{"favourite":4761,"name":"学活！ 第二季","url":"http://bangumi.bilibili.com/anime/586","count":282000.0},{"favourite":4759,"name":"鲁邦三世：次元大介的墓碑","url":"http://bangumi.bilibili.com/anime/2834","count":130000.0},{"favourite":4754,"name":"黑礁 特典小剧场","url":"http://bangumi.bilibili.com/anime/3842","count":186000.0},{"favourite":4754,"name":"战国☆天堂 -极-","url":"http://bangumi.bilibili.com/anime/892","count":89000.0},{"favourite":4749,"name":"第三飞行少女队","url":"http://bangumi.bilibili.com/anime/4148","count":151000.0},{"favourite":4748,"name":"蓝龙","url":"http://bangumi.bilibili.com/anime/1281","count":53000.0},{"favourite":4742,"name":"恋恋七人组","url":"http://bangumi.bilibili.com/anime/5090","count":48000.0}]