{"code":0,"message":"success","result":{"count":"2898","list":[{"cover":"http://i0.hdslb.com/bfs/bangumi/f8d085f90c71d468db5cc791cb51d6ceee05f286.jpg","favorites":7191,"is_finish":2,"newest_ep_index":"10","pub_time":964627200,"season_id":"3088","season_status":2,"title":"哥谭妹子 第一季","total_count":10,"update_time":1420469714,"url":"http://bangumi.bilibili.com/anime/3088","week":"-1"},{"cover":"http://i0.hdslb.com/bfs/bangumi/01bcdd1b11e153a52454877f724b68aac9b6a13b.jpg","favorites":7181,"is_finish":2,"newest_ep_index":"1","pub_time":1368288000,"season_id":"602","season_status":2,"title":"天使的水果糖","total_count":1,"update_time":1368373532,"url":"http://bangumi.bilibili.com/anime/602","week":"-1"},{"cover":"http://i0.hdslb.com/bfs/bangumi/8557eba33799cec4c180d0e13013878ef16ea470.jpg","favorites":7151,"is_finish":2,"newest_ep_index":"51","pub_time":1270224000,"season_id":"4680","season_status":2,"title":"SD敢达三国传 Brave Battle Warriors","total_count":51,"update_time":1491018089,"url":"http://bangumi.bilibili.com/anime/4680","week":"-1"},{"cover":"http://i0.hdslb.com/bfs/bangumi/9effab396b56358d6dd25ba6a01b516527f1639f.jpg","favorites":7141,"is_finish":2,"newest_ep_index":"12","pub_time":1349366400,"season_id":"734","season_status":2,"title":"向阳素描×蜂窝","total_count":12,"update_time":1356086672,"url":"http://bangumi.bilibili.com/anime/734","week":"5"},{"cover":"http://i0.hdslb.com/bfs/bangumi/7ac4f5a5499fefee5c7e37e480e2b6190cd09e74.jpg","favorites":7137,"is_finish":2,"newest_ep_index":"1","pub_time":1395331200,"season_id":"1494","season_status":2,"title":"战国无双SP 真田之章","total_count":1,"update_time":1489632136,"url":"http://bangumi.bilibili.com/anime/1494","week":"0"},{"cover":"http://i0.hdslb.com/bfs/bangumi/fec727bba852d862bcd2010f405cea350771c0f5.jpg","favorites":7130,"is_finish":2,"newest_ep_index":"3","pub_time":780940800,"season_id":"521","season_status":2,"title":"科学小飞侠 OVA（1994）","total_count":3,"update_time":1460701701,"url":"http://bangumi.bilibili.com/anime/521","week":"6"},{"cover":"http://i0.hdslb.com/bfs/bangumi/a44a83e126301bf42466de45635798d94933c31d.jpg","favorites":7111,"is_finish":2,"newest_ep_index":"12","pub_time":1484490600,"season_id":"5883","season_status":2,"title":"宇宙警探elDLIVE 中文配音版","total_count":12,"update_time":1491748200,"url":"http://bangumi.bilibili.com/anime/5883","week":"0"},{"cover":"http://i0.hdslb.com/bfs/bangumi/22ebeabeebcbbd1d96ae48761bd358b7f32aebfb.jpg","favorites":7084,"is_finish":2,"newest_ep_index":"1","pub_time":1298649600,"season_id":"3565","season_status":2,"title":"超时空要塞F 恋离飞翼 后篇","total_count":1,"update_time":1460357244,"url":"http://bangumi.bilibili.com/anime/3565","week":"6"},{"cover":"http://i0.hdslb.com/bfs/bangumi/496d4d42b3ab2845c036445c1ddfa50d887807f5.jpg","favorites":7083,"is_finish":2,"newest_ep_index":"13","pub_time":1073923200,"season_id":"1912","season_status":2,"title":"向北","total_count":13,"update_time":1368855162,"url":"http://bangumi.bilibili.com/anime/1912","week":"2"},{"cover":"http://i0.hdslb.com/bfs/bangumi/e87a2a8d88d9406003e575a7fa9ef37511e8464c.jpg","favorites":7083,"is_finish":2,"newest_ep_index":"24","pub_time":1420646400,"season_id":"1698","season_status":2,"title":"PUNKISS！2次元","total_count":24,"update_time":1434673799,"url":"http://bangumi.bilibili.com/anime/1698","week":"4"},{"cover":"http://i0.hdslb.com/bfs/bangumi/12a124fd6e1b8c9c407076c6b03f282c6a8b1b09.jpg","favorites":7073,"is_finish":2,"newest_ep_index":"95","pub_time":821203200,"season_id":"5412","season_status":2,"title":"浪客剑心","total_count":94,"update_time":1470020627,"url":"http://bangumi.bilibili.com/anime/5412","week":"3"},{"cover":"http://i0.hdslb.com/bfs/bangumi/09da4bf8a8fedd4f161403683c75fe2b55b09d15.jpg","favorites":7071,"is_finish":2,"newest_ep_index":"3","pub_time":1296144000,"season_id":"2933","season_status":2,"title":".HACK//Quantum","total_count":3,"update_time":1446297141,"url":"http://bangumi.bilibili.com/anime/2933","week":"-1"},{"cover":"http://i0.hdslb.com/bfs/bangumi/4cb122849d2775b36a38a64882d2c2f4ec324e16.jpg","favorites":7059,"is_finish":2,"newest_ep_index":"26","pub_time":1080921600,"season_id":"1905","season_status":2,"title":"爱你宝贝","total_count":26,"update_time":1347514945,"url":"http://bangumi.bilibili.com/anime/1905","week":"6"},{"cover":"http://i0.hdslb.com/bfs/bangumi/4f10ff0425e84d4dd92615da0fa90e6a6bddd42b.jpg","favorites":7043,"is_finish":2,"newest_ep_index":"26","pub_time":1097078400,"season_id":"1888","season_status":2,"title":"次元舰队","total_count":26,"update_time":1377773725,"url":"http://bangumi.bilibili.com/anime/1888","week":"4"},{"cover":"http://i0.hdslb.com/bfs/bangumi/c6019c32825dc8e4b7048b856af8629986496b2b.jpg","favorites":7027,"is_finish":2,"newest_ep_index":"38","pub_time":607795200,"season_id":"2392","season_status":2,"title":"天空战记","total_count":38,"update_time":1296485358,"url":"http://bangumi.bilibili.com/anime/2392","week":"4"},{"cover":"http://i0.hdslb.com/bfs/bangumi/b7f9655aff39cd49e76124d9e0805b4cb0a9940f.jpg","favorites":7024,"is_finish":2,"newest_ep_index":"13","pub_time":1254326400,"season_id":"3813","season_status":2,"title":"机巧魔神2","total_count":13,"update_time":1461134379,"url":"http://bangumi.bilibili.com/anime/3813","week":"4"},{"cover":"http://i0.hdslb.com/bfs/bangumi/a0d78115c4723a5bc83d37709528e05d85bbbfd7.jpg","favorites":7018,"is_finish":2,"newest_ep_index":"26","pub_time":1238860800,"season_id":"1131","season_status":2,"title":"豹头王传说","total_count":26,"update_time":1412907101,"url":"http://bangumi.bilibili.com/anime/1131","week":"1"},{"cover":"http://i0.hdslb.com/bfs/bangumi/170a15388a44a826c0e0afb4644b81fba981590a.jpg","favorites":7007,"is_finish":2,"newest_ep_index":"3","pub_time":1437062400,"season_id":"3788","season_status":2,"title":"偶像大师 灰姑娘女孩 第二季 OVA","total_count":3,"update_time":1461048274,"url":"http://bangumi.bilibili.com/anime/3788","week":"-1"},{"cover":"http://i0.hdslb.com/bfs/bangumi/60a71ac9037cea47ae2aff7814877fdb36ff13fd.jpg","favorites":6992,"is_finish":2,"newest_ep_index":"1","pub_time":932140800,"season_id":"5757","season_status":2,"title":"无印：梦幻的精灵宝可梦洛奇亚爆诞","total_count":1,"update_time":1481093163,"url":"http://bangumi.bilibili.com/anime/5757","week":"2"},{"cover":"http://i0.hdslb.com/bfs/bangumi/e13e4cee7c0a8edaf2a95fdc4dc554ec93115778.jpg","favorites":6966,"is_finish":2,"newest_ep_index":"1","pub_time":1035561600,"season_id":"5581","season_status":2,"title":"水之语","total_count":1,"update_time":1475806953,"url":"http://bangumi.bilibili.com/anime/5581","week":"6"}],"pages":"145"}}