{"code":0,"message":"success","result":{"count":"2898","list":[{"cover":"http://i0.hdslb.com/bfs/bangumi/a53dad2d453749986dd621467aba5662b7527c89.jpg","favorites":4232,"is_finish":2,"newest_ep_index":"5","pub_time":1467302400,"season_id":"5405","season_status":2,"title":"千叶脚踏板","total_count":6,"update_time":1472444756,"url":"http://bangumi.bilibili.com/anime/5405","week":"-1"},{"cover":"http://i0.hdslb.com/bfs/bangumi/bc01321ec67a2a97a1e5f9cdd2d7fbcf41eeb7f6.jpg","favorites":4219,"is_finish":2,"newest_ep_index":"12","pub_time":1041955200,"season_id":"1959","season_status":2,"title":"骇客时空  黄昏的腕轮传说","total_count":12,"update_time":1489904677,"url":"http://bangumi.bilibili.com/anime/1959","week":"3"},{"cover":"http://i0.hdslb.com/bfs/bangumi/a7951adf2d78dba4648ba93653778bc2d958548f.jpg","favorites":4213,"is_finish":2,"newest_ep_index":"4-5","pub_time":1286208000,"season_id":"1007","season_status":2,"title":"面包咪咪","total_count":5,"update_time":1289903247,"url":"http://bangumi.bilibili.com/anime/1007","week":"2"},{"cover":"http://i0.hdslb.com/bfs/bangumi/2d676042e5e175596a11df7c7c929340839909dd.jpg","favorites":4208,"is_finish":2,"newest_ep_index":"50","pub_time":1044115200,"season_id":"1992","season_status":2,"title":"明日的娜嘉","total_count":50,"update_time":1374684859,"url":"http://bangumi.bilibili.com/anime/1992","week":"1"},{"cover":"http://i0.hdslb.com/bfs/bangumi/4c751f95a2ab61551ca3da0d15e930888aac263a.jpg","favorites":4208,"is_finish":2,"newest_ep_index":"4","pub_time":780336000,"season_id":"1343","season_status":2,"title":"逮捕令 OVA","total_count":4,"update_time":1332092368,"url":"http://bangumi.bilibili.com/anime/1343","week":"0"},{"cover":"http://i0.hdslb.com/bfs/bangumi/fe916802de1c5e1c48736fade9de80dcd38cd136.jpg","favorites":4207,"is_finish":2,"newest_ep_index":"50","pub_time":1065456000,"season_id":"3914","season_status":2,"title":"魔法咪路咪路 Golden","total_count":24,"update_time":1462257044,"url":"http://bangumi.bilibili.com/anime/3914","week":"2"},{"cover":"http://i0.hdslb.com/bfs/bangumi/088ca4e4e683b0b9be62cb4bdc168f256ec61120.jpg","favorites":4196,"is_finish":2,"newest_ep_index":"1","pub_time":1486742400,"season_id":"5929","season_status":2,"title":"青鬼 THE ANIMATION","total_count":1,"update_time":1486816625,"url":"http://bangumi.bilibili.com/anime/5929","week":"-1"},{"cover":"http://i0.hdslb.com/bfs/bangumi/395207f3bc8e5924e6c5117196ded38163cad637.jpg","favorites":4190,"is_finish":2,"newest_ep_index":"2","pub_time":1249833600,"season_id":"3835","season_status":2,"title":"交响情人梦 OAD","total_count":2,"update_time":1461555406,"url":"http://bangumi.bilibili.com/anime/3835","week":"-1"},{"cover":"http://i0.hdslb.com/bfs/bangumi/575fb13512b23f8795e77e0c284fb9c8cf55df04.jpg","favorites":4184,"is_finish":2,"newest_ep_index":"2","pub_time":1166716800,"season_id":"1317","season_status":2,"title":"冬日花园","total_count":2,"update_time":1329298232,"url":"http://bangumi.bilibili.com/anime/1317","week":"5"},{"cover":"http://i0.hdslb.com/bfs/bangumi/67875b3958e67ec0012649b0c5501fd9129e4aec.jpg","favorites":4178,"is_finish":2,"newest_ep_index":"16","pub_time":915552000,"season_id":"2220","season_status":2,"title":"日本第一男人之魂","total_count":16,"update_time":1284795286,"url":"http://bangumi.bilibili.com/anime/2220","week":"3"},{"cover":"http://i0.hdslb.com/bfs/bangumi/ab814126244e80391b27f646f90b15ecec2d637e.jpg","favorites":4173,"is_finish":2,"newest_ep_index":"28","pub_time":939052800,"season_id":"2135","season_status":2,"title":"钢铁天使核桃","total_count":28,"update_time":1370611234,"url":"http://bangumi.bilibili.com/anime/2135","week":"3"},{"cover":"http://i0.hdslb.com/bfs/bangumi/65d8a9cc8b5bf29e249dd628fa110467ea1d30cb.jpg","favorites":4167,"is_finish":2,"newest_ep_index":"1","pub_time":1329235200,"season_id":"4610","season_status":2,"title":"百合星人奈绪子OVA","total_count":1,"update_time":1465623003,"url":"http://bangumi.bilibili.com/anime/4610","week":"-1"},{"cover":"http://i0.hdslb.com/bfs/bangumi/16de361f00e7481ee1ea65835a89c9c5909babe0.jpg","favorites":4161,"is_finish":2,"newest_ep_index":"1","pub_time":1437667200,"season_id":"5488","season_status":2,"title":"天体的秩序SP","total_count":1,"update_time":1473392445,"url":"http://bangumi.bilibili.com/anime/5488","week":"-1"},{"cover":"http://i0.hdslb.com/bfs/bangumi/5b196510c9f547c7f791e6ad083a8452cfd0bc65.jpg","favorites":4161,"is_finish":2,"newest_ep_index":"24","pub_time":1159718400,"season_id":"1409","season_status":2,"title":"南瓜剪刀","total_count":24,"update_time":1382950445,"url":"http://bangumi.bilibili.com/anime/1409","week":"2"},{"cover":"http://i0.hdslb.com/bfs/bangumi/66d4c15b329e41388b8a9fe70cc332ee3ac6ad5c.jpg","favorites":4157,"is_finish":2,"newest_ep_index":"26","pub_time":828374400,"season_id":"2300","season_status":2,"title":"天空之艾斯嘉科尼","total_count":26,"update_time":1373393982,"url":"http://bangumi.bilibili.com/anime/2300","week":"2"},{"cover":"http://i0.hdslb.com/bfs/bangumi/84dc39f570f8b8f573004b06ecf2f04e1921ae48.jpg","favorites":4145,"is_finish":2,"newest_ep_index":"53","pub_time":252432000,"season_id":"3216","season_status":2,"title":"佩琳物语","total_count":53,"update_time":1450320166,"url":"http://bangumi.bilibili.com/anime/3216","week":"-1"},{"cover":"http://i0.hdslb.com/bfs/bangumi/a4cc20956ccd7f538ddf29d4cabca69da55ac650.jpg","favorites":4130,"is_finish":2,"newest_ep_index":"1","pub_time":353347200,"season_id":"2550","season_status":2,"title":"哆啦A梦 大雄的宇宙开拓史","total_count":1,"update_time":1423814516,"url":"http://bangumi.bilibili.com/anime/2550","week":"0"},{"cover":"http://i0.hdslb.com/bfs/bangumi/ac5fe32dcdb50b2741896a4501bb24fe577489d9.jpg","favorites":4122,"is_finish":2,"newest_ep_index":"3","pub_time":1006272000,"season_id":"5278","season_status":2,"title":"秋之回忆 OVA","total_count":3,"update_time":1469084108,"url":"http://bangumi.bilibili.com/anime/5278","week":"3"},{"cover":"http://i0.hdslb.com/bfs/bangumi/1236e3bf591cb1ad7b0b90488b93dd00f5a3c35d.jpg","favorites":4119,"is_finish":2,"newest_ep_index":"1","pub_time":1477065600,"season_id":"5704","season_status":2,"title":"人狼暗号1951","total_count":1,"update_time":1479091904,"url":"http://bangumi.bilibili.com/anime/5704","week":"6"},{"cover":"http://i0.hdslb.com/bfs/bangumi/595bbec5060270fc80a742176fbd11866cdc0edd.jpg","favorites":4115,"is_finish":2,"newest_ep_index":"13","pub_time":1104508800,"season_id":"5134","season_status":2,"title":"魔法少女加奈","total_count":13,"update_time":1467947094,"url":"http://bangumi.bilibili.com/anime/5134","week":"6"}],"pages":"145"}}