{"code":0,"message":"success","result":{"count":"2898","list":[{"cover":"http://i0.hdslb.com/bfs/bangumi/bfc82e6fad4f3a4fea1ce7f85b9060a1f77fdf97.jpg","favorites":141198,"is_finish":2,"newest_ep_index":"11","pub_time":1476288000,"season_id":"5516","season_status":2,"title":"编舟记","total_count":11,"update_time":1482465674,"url":"http://bangumi.bilibili.com/anime/5516","week":"4"},{"cover":"http://i0.hdslb.com/bfs/bangumi/37300216579d941a6dc2f318ef9cc0b18e8fdea6.jpg","favorites":140809,"is_finish":2,"newest_ep_index":"13","pub_time":1459440000,"season_id":"3459","season_status":2,"title":"宇宙巡警露露子","total_count":13,"update_time":1466776802,"url":"http://bangumi.bilibili.com/anime/3459","week":"5"},{"cover":"http://i0.hdslb.com/bfs/bangumi/dc99c5c10c3705fd5d0dbdbaf1ef1cf7e7595588.jpg","favorites":140592,"is_finish":1,"newest_ep_index":"4","pub_time":1490407200,"season_id":"6008","season_status":2,"title":"梦王国与沉睡的100王子 短篇动画","total_count":10,"update_time":1498356000,"url":"http://bangumi.bilibili.com/anime/6008","week":"-1"},{"cover":"http://i0.hdslb.com/bfs/bangumi/ff85b64a18556bb5c0a28a2168048f7cd3721ce3.jpg","favorites":140416,"is_finish":2,"newest_ep_index":"2","pub_time":1405094400,"season_id":"2793","season_status":2,"title":"K MISSING KINGS","total_count":2,"update_time":1452073372,"url":"http://bangumi.bilibili.com/anime/2793","week":"6"},{"cover":"http://i0.hdslb.com/bfs/bangumi/d66cd40a9729800e8e7570391779b3f8eb547d5d.jpg","favorites":140409,"is_finish":2,"newest_ep_index":"13","pub_time":1364918400,"season_id":"572","season_status":2,"title":"KARNEVAL狂欢节","total_count":13,"update_time":1449629202,"url":"http://bangumi.bilibili.com/anime/572","week":"3"},{"cover":"http://i0.hdslb.com/bfs/bangumi/59b3506e9791a9319f2e4cac80e4937d7e6fe766.jpg","favorites":140307,"is_finish":2,"newest_ep_index":"12","pub_time":1445616000,"season_id":"2894","season_status":2,"title":"RWBY 第三季","total_count":12,"update_time":1455593808,"url":"http://bangumi.bilibili.com/anime/2894","week":"-1"},{"cover":"http://i0.hdslb.com/bfs/bangumi/c897c607f6d2e40a18cb9656aed48ea26c252721.jpg","favorites":140078,"is_finish":1,"newest_ep_index":"-1","pub_time":1499097600,"season_id":"6311","season_status":2,"title":"笨女孩","total_count":12,"update_time":1499097600,"url":"http://bangumi.bilibili.com/anime/6311","week":"2"},{"cover":"http://i0.hdslb.com/bfs/bangumi/d9b08ef7546f5dff4d05e402aa3061c9471d69b8.jpg","favorites":139634,"is_finish":2,"newest_ep_index":"24","pub_time":1207411200,"season_id":"1247","season_status":2,"title":"我家有个狐仙大人","total_count":24,"update_time":1280547268,"url":"http://bangumi.bilibili.com/anime/1247","week":"3"},{"cover":"http://i0.hdslb.com/bfs/bangumi/84488991f62c9be2381fd7a447e1309af5f18189.jpg","favorites":139566,"is_finish":2,"newest_ep_index":"13","pub_time":1199462400,"season_id":"2910","season_status":2,"title":"真实之泪","total_count":13,"update_time":1446000494,"url":"http://bangumi.bilibili.com/anime/2910","week":"6"},{"cover":"http://i0.hdslb.com/bfs/bangumi/e7977d6fca4a360428e5252bca5dc79e1fd17087.jpg","favorites":138776,"is_finish":2,"newest_ep_index":"12","pub_time":1428768000,"season_id":"1677","season_status":2,"title":"山田君与7人魔女","total_count":12,"update_time":1495015140,"url":"http://bangumi.bilibili.com/anime/1677","week":"1"},{"cover":"http://i0.hdslb.com/bfs/bangumi/6b4a565e9c06fa7368f97254bfe5ad2db61cf9d1.jpg","favorites":138159,"is_finish":2,"newest_ep_index":"26","pub_time":1475589300,"season_id":"5549","season_status":2,"title":"忍者少女千鸟","total_count":26,"update_time":1490709302,"url":"http://bangumi.bilibili.com/anime/5549","week":"2"},{"cover":"http://i0.hdslb.com/bfs/bangumi/4dd345a0aaa9d8d49c0c80f5f79d2aefa85ad4ea.jpg","favorites":137272,"is_finish":2,"newest_ep_index":"12","pub_time":1191600000,"season_id":"1181","season_status":2,"title":"悠久之翼","total_count":12,"update_time":1320411607,"url":"http://bangumi.bilibili.com/anime/1181","week":"0"},{"cover":"http://i0.hdslb.com/bfs/bangumi/96bc6afb0060565675867bb6052482de783bb4d8.jpg","favorites":136653,"is_finish":2,"newest_ep_index":"13","pub_time":1459440000,"season_id":"3499","season_status":2,"title":"影鳄 承","total_count":12,"update_time":1466777341,"url":"http://bangumi.bilibili.com/anime/3499","week":"5"},{"cover":"http://i0.hdslb.com/bfs/bangumi/9fcbfadd83feb3e7b58d3de63cd52f416df9ec15.jpg","favorites":136563,"is_finish":2,"newest_ep_index":"12","pub_time":1107705600,"season_id":"1593","season_status":2,"title":"搞笑漫画日和","total_count":12,"update_time":1421733082,"url":"http://bangumi.bilibili.com/anime/1593","week":"1"},{"cover":"http://i0.hdslb.com/bfs/bangumi/8635450b59ca6d252b919b25220093772fd2e311.jpg","favorites":136535,"is_finish":2,"newest_ep_index":"12","pub_time":1286380800,"season_id":"1003","season_status":2,"title":"咎狗之血","total_count":12,"update_time":1334206905,"url":"http://bangumi.bilibili.com/anime/1003","week":"5"},{"cover":"http://i0.hdslb.com/bfs/bangumi/2484dcad56041632c44fbaac91852fd6c7d775ab.jpg","favorites":136343,"is_finish":2,"newest_ep_index":"13","pub_time":1302192000,"season_id":"566","season_status":2,"title":"恶魔阿萨谢尔在召唤你 第一季","total_count":13,"update_time":1309579573,"url":"http://bangumi.bilibili.com/anime/566","week":"6"},{"cover":"http://i0.hdslb.com/bfs/bangumi/58ee2dd37eefd284dff3d5b8f91cfbc38cb05367.jpg","favorites":135792,"is_finish":2,"newest_ep_index":"24","pub_time":1191686400,"season_id":"1332","season_status":2,"title":"出租魔法使","total_count":24,"update_time":1291440485,"url":"http://bangumi.bilibili.com/anime/1332","week":"0"},{"cover":"http://i0.hdslb.com/bfs/bangumi/958da3eeb0322b58e59698b535f056839ef1d9fa.jpg","favorites":134977,"is_finish":2,"newest_ep_index":"12","pub_time":1467817200,"season_id":"5039","season_status":2,"title":"OZMAFIA!!","total_count":12,"update_time":1474470010,"url":"http://bangumi.bilibili.com/anime/5039","week":"3"},{"cover":"http://i0.hdslb.com/bfs/bangumi/170a15388a44a826c0e0afb4644b81fba981590a.jpg","favorites":134895,"is_finish":2,"newest_ep_index":"13","pub_time":1420732800,"season_id":"1509","season_status":2,"title":"偶像大师 灰姑娘女孩","total_count":13,"update_time":1428683413,"url":"http://bangumi.bilibili.com/anime/1509","week":"0"},{"cover":"http://i0.hdslb.com/bfs/bangumi/909c6b7bde4e761b05d266dfbb4d33d98b78c5ce.jpg","favorites":134528,"is_finish":2,"newest_ep_index":"2","pub_time":1487430000,"season_id":"5933","season_status":2,"title":"龙的牙医","total_count":2,"update_time":1488034809,"url":"http://bangumi.bilibili.com/anime/5933","week":"6"}],"pages":"145"}}